ha_wireguard_api/__init__.py
ha_wireguard_api/api.py
ha_wireguard_api/const.py
ha_wireguard_api/exceptions.py
ha_wireguard_api/model.py
ha_wireguard_api/py.typed
ha_wireguard_api-0.2.4.dist-info/LICENSE
ha_wireguard_api-0.2.4.dist-info/METADATA
ha_wireguard_api-0.2.4.dist-info/WHEEL
ha_wireguard_api-0.2.4.dist-info/top_level.txt
ha_wireguard_api-0.2.4.dist-info/RECORD
