Metadata-Version: 2.1
Name: ha_wireguard_api
Version: 0.2.4
Summary: Asynchronous client for WireGuard status API
Author-email: Niels Perfors <niels.perfors1987@gmail.com>
License: MIT
Project-URL: Homepage, https://github.com/niro1987/ha-wireguard-api
Project-URL: Documentation, https://github.com/niro1987/ha-wireguard-api
Project-URL: Repository, https://github.com/niro1987/ha-wireguard-api.git
Project-URL: Issues, https://github.com/niro1987/ha-wireguard-api/issues
Keywords: homeassistant,wireguard
Classifier: Intended Audience :: Developers
Classifier: License :: OSI Approved :: MIT License
Classifier: Programming Language :: Python :: 3.11
Classifier: Programming Language :: Python :: 3.12
Requires-Python: >=3.11
License-File: LICENSE
Requires-Dist: aiohttp >=3.0.0
Provides-Extra: dev
Provides-Extra: test
